{
 "actions": [],
 "allow_rename": 1,
 "creation": "2024-08-14 14:11:43.983465",
 "doctype": "DocType",
 "editable_grid": 1,
 "engine": "InnoDB",
 "field_order": [
  "date",
  "medium",
  "summary"
 ],
 "fields": [
  {
   "fieldname": "date",
   "fieldtype": "Date",
   "label": "Date"
  },
  {
   "fieldname": "medium",
   "fieldtype": "Select",
   "label": "Medium",
   "options": "Email\nPhone\nIn-Person"
  },
  {
   "fieldname": "summary",
   "fieldtype": "Text",
   "label": "Summary"
  }
 ],
 "index_web_pages_for_search": 1,
 "istable": 1,
 "links": [],
 "modified": "2024-08-14 14:12:55.273408",
 "modified_by": "Administrator",
 "module": "app1",
 "name": "Communication Log",
 "owner": "Administrator",
 "permissions": [],
 "sort_field": "modified",
 "sort_order": "DESC",
 "states": []
}